aiolibgen/__init__.py
aiolibgen/cli.py
aiolibgen/client.py
aiolibgen/exceptions.py
aiolibgen-0.2.0.dist-info/LICENSE
aiolibgen-0.2.0.dist-info/METADATA
aiolibgen-0.2.0.dist-info/WHEEL
aiolibgen-0.2.0.dist-info/entry_points.txt
aiolibgen-0.2.0.dist-info/top_level.txt
aiolibgen-0.2.0.dist-info/RECORD
