Metadata-Version: 2.1
Name: aiolibgen
Version: 0.2.0
Summary: UNKNOWN
Home-page: https://github.com/izihawa/aiolibgen
Author: Pasha Podolsky
License: MIT
Platform: UNKNOWN
Classifier: Topic :: Utilities
Requires-Dist: aiobaseclient (>=0.1.0)
Requires-Dist: fire (>=0.3.1)
